d2nt/__init__.py
d2nt/core.py
d2nt/filters.py
d2nt/utils.py
d2nt-0.1.3.dist-info/licenses/LICENSE
d2nt-0.1.3.dist-info/METADATA
d2nt-0.1.3.dist-info/WHEEL
d2nt-0.1.3.dist-info/top_level.txt
d2nt-0.1.3.dist-info/RECORD
