Metadata-Version: 2.4
Name: d2nt
Version: 0.1.3
Summary: D2NT: A High-Performing Depth-to-Normal Translator
Author: Yi Feng, Bohuan Xue, Ming Liu, Qijun Chen, and Rui Fan
License: MIT
Project-URL: Homepage, https://mias.group/D2NT
Project-URL: Documentation, https://github.com/fengyi233/depth-to-normal-translator
Project-URL: Repository, https://github.com/fengyi233/depth-to-normal-translator
Project-URL: Bug Tracker, https://github.com/fengyi233/depth-to-normal-translator/issues
Keywords: depth,normal,computer-vision,robotics,3d-reconstruction
Classifier: Development Status :: 4 - Beta
Classifier: Intended Audience :: Science/Research
Classifier: Intended Audience :: Developers
Classifier: Topic :: Scientific/Engineering :: Image Processing
Classifier: Topic :: Scientific/Engineering :: Artificial Intelligence
Classifier: Programming Language :: Python :: 3
Classifier: Programming Language :: Python :: 3.7
Classifier: Programming Language :: Python :: 3.8
Classifier: Programming Language :: Python :: 3.9
Classifier: Programming Language :: Python :: 3.10
Classifier: Programming Language :: Python :: 3.11
Requires-Python: >=3.7
License-File: LICENSE
Requires-Dist: numpy>=1.20.0
Requires-Dist: opencv-python>=4.0.0
Provides-Extra: dev
Requires-Dist: matplotlib>=3.5.0; extra == "dev"
Requires-Dist: pytest>=7.0.0; extra == "dev"
Dynamic: license-file
